pytcp/__init__.py
pytcp/config.py
pytcp/py.typed
pytcp-2.7.10.dist-info/licenses/LICENSE
pytcp-2.7.10.dist-info/METADATA
pytcp-2.7.10.dist-info/WHEEL
pytcp-2.7.10.dist-info/top_level.txt
pytcp-2.7.10.dist-info/RECORD
