Metadata-Version: 2.4
Name: PyTCP
Version: 2.7.10
Summary: TCP/IP stack written in Python.
Author-email: Sebastian Majewski <ccie18643@gmail.com>
License-Expression: GPL-3.0-or-later
Project-URL: Homepage, https://github.com/ccie18643/PyTCP
Project-URL: Bug Tracker, https://github.com/ccie18643/PyTCP/issues
Keywords: pytcp,stack,networking,tcp,ip,ipv4,ipv6,arp,ethernet,icmp
Classifier: Programming Language :: Python :: 3.12
Classifier: Development Status :: 3 - Alpha
Classifier: Operating System :: POSIX :: Linux
Classifier: Natural Language :: English
Classifier: Environment :: Console
Classifier: Topic :: System :: Networking
Classifier: Typing :: Typed
Requires-Python: >=3.12
License-File: LICENSE
Dynamic: license-file
